{
  "pipeline_version": "2.1",
  "timestamp": "2026-06-07 05:12:38 UTC",
  "input_corpus": "/home/runner/work/MutualfundFAQ_RAGbot/MutualfundFAQ_RAGbot/data/corpus_runs/20260607T051148_502889Z",
  "output_directory": "data/phase2_results",
  "strategy": {
    "bm25_weight": 0.75,
    "vector_weight": 0.25,
    "use_rrf": true,
    "embedding_model": "BAAI/bge-small-en-v1.5",
    "index_type": "Flat"
  },
  "chunking": {
    "total_before_filtering": 53,
    "total_after_filtering": 53,
    "filter_ratio": 1.0,
    "processing_time_seconds": 0.6293327808380127,
    "summary": {
      "total_chunks": 53,
      "average_chunk_size": 348.1698113207547,
      "content_types": {
        "fund_info": 44,
        "mixed": 9
      },
      "amc_distribution": {
        "Choice Mutual Fund": 3,
        "Unifi Mutual Fund": 4,
        "Union Mutual Fund": 16,
        "ICICI Prudential Mutual Fund": 14,
        "LIC Mutual Fund": 16
      },
      "average_financial_density": 0.124349044670737
    }
  },
  "indexing": {
    "processing_time_seconds": 4.9793267250061035,
    "stats": {
      "status": "Index loaded",
      "ntotal": 53,
      "dimension": 384,
      "is_trained": true,
      "type": "Flat",
      "index_type": "flat",
      "n_vectors": 53,
      "nlist": null,
      "nprobe": null,
      "add_time_seconds": 4.315376281738281e-05,
      "memory_usage_mb": 0.07763671875
    }
  },
  "validation": {
    "amc_routing_rate": 1.0,
    "queries": [
      {
        "query": "What is the NAV of Choice Mutual Fund?",
        "expected_amc": "Choice Mutual Fund",
        "top_amc": "Choice Mutual Fund",
        "amc_routing_ok": true,
        "results_count": 3,
        "top_score": 0.06499351887152116,
        "search_time_ms": 20.363330841064453
      },
      {
        "query": "What are the expense ratios for Union Mutual Fund schemes?",
        "expected_amc": "Union Mutual Fund",
        "top_amc": "Union Mutual Fund",
        "amc_routing_ok": true,
        "results_count": 5,
        "top_score": 0.06449604103936657,
        "search_time_ms": 19.507169723510742
      },
      {
        "query": "Tell me about SIP minimum for Unifi Liquid Fund",
        "expected_amc": "Unifi Mutual Fund",
        "top_amc": "Unifi Mutual Fund",
        "amc_routing_ok": true,
        "results_count": 1,
        "top_score": 0.09737704918032787,
        "search_time_ms": 19.193649291992188
      },
      {
        "query": "ICICI Prudential mutual fund schemes",
        "expected_amc": "ICICI Prudential Mutual Fund",
        "top_amc": "ICICI Prudential Mutual Fund",
        "amc_routing_ok": true,
        "results_count": 5,
        "top_score": 0.04598360655737706,
        "search_time_ms": 19.417762756347656
      },
      {
        "query": "LIC Mutual Fund exit load",
        "expected_amc": "LIC Mutual Fund",
        "top_amc": "LIC Mutual Fund",
        "amc_routing_ok": true,
        "results_count": 5,
        "top_score": 0.06344050766790059,
        "search_time_ms": 17.357587814331055
      }
    ]
  },
  "files": {
    "chunks_file": "data/phase2_results/chunks/chunks.json",
    "retrieval_dir": "data/phase2_results/retrieval",
    "indexes_dir": "data/phase2_results/indexes"
  }
}
